dataset2vec/__init__.py
dataset2vec/config.py
dataset2vec/data.py
dataset2vec/model.py
dataset2vec/train.py
dataset2vec/utils.py
dataset2vec-1.0.0.dist-info/LICENSE
dataset2vec-1.0.0.dist-info/METADATA
dataset2vec-1.0.0.dist-info/WHEEL
dataset2vec-1.0.0.dist-info/top_level.txt
dataset2vec-1.0.0.dist-info/RECORD
