Metadata-Version: 2.1
Name: dataset2vec
Version: 1.0.0
Summary: Package for training and further usage of Dataset2Vec meta-model.
Author-email: Antoni Zajko <antoni.zajko.1@gmail.com>
Project-URL: Homepage, https://github.com/azoz01/dataset2vec
Classifier: Programming Language :: Python :: 3
Classifier: License :: OSI Approved :: MIT License
Classifier: Operating System :: OS Independent
Requires-Python: >=3.9
License-File: LICENSE
Requires-Dist: torch >=2.3.0
Requires-Dist: pandas >=2.2.2
Requires-Dist: numpy >=1.26.4
Requires-Dist: scikit-learn >=1.4.2
Requires-Dist: pydantic >=2.7.1
Requires-Dist: pytorch-lightning[extra] >=2.2.3
